{"key_messages": [{"message": "Basecamp makes project management simple and intuitive.", "context": "Most project management systems are overwhelming, inadequate, bewildering, or chaotic. Basecamp aims to simplify this.", "type": "Value Proposition", "confidence": 90}, {"message": "Basecamp: Project management made easy.", "context": "TITLE: Basecamp: Project management software, online collaboration", "type": "Tagline", "confidence": 85}, {"message": "Born out of the necessity to stop embarrassing ourselves.", "context": "Born out of desperate necessity to stop embarrassing ourselves in front of our clients, the story of how Basecamp was born is likely your story, too.", "type": "Value Proposition", "confidence": 80}, {"message": "Manage everything you need on a single screen with Basecamp.", "context": "Can I see everything I need to do on a single screen? Can I see everything that\u2019s overdue on a single screen?", "type": "Value Proposition", "confidence": 85}, {"message": "Basecamp supports seamless integration with popular apps.", "context": "Can I link up files from Google Docs, Figma, Dropbox, Airtable, and other apps?", "type": "Value Proposition", "confidence": 75}]}